projects/__init__.py
pytorch3d/_C.cpython-311-x86_64-linux-gnu.so
pytorch3d/__init__.py
pytorch3d/common/__init__.py
pytorch3d/common/compat.py
pytorch3d/common/datatypes.py
pytorch3d/common/linear_with_repeat.py
pytorch3d/common/workaround/__init__.py
pytorch3d/common/workaround/symeig3x3.py
pytorch3d/common/workaround/utils.py
pytorch3d/csrc/ext.cpp
pytorch3d/csrc/ball_query/ball_query.cu
pytorch3d/csrc/ball_query/ball_query_cpu.cpp
pytorch3d/csrc/blending/sigmoid_alpha_blend.cu
pytorch3d/csrc/blending/sigmoid_alpha_blend_cpu.cpp
pytorch3d/csrc/compositing/alpha_composite.cu
pytorch3d/csrc/compositing/alpha_composite_cpu.cpp
pytorch3d/csrc/compositing/norm_weighted_sum.cu
pytorch3d/csrc/compositing/norm_weighted_sum_cpu.cpp
pytorch3d/csrc/compositing/weighted_sum.cu
pytorch3d/csrc/compositing/weighted_sum_cpu.cpp
pytorch3d/csrc/face_areas_normals/face_areas_normals.cu
pytorch3d/csrc/face_areas_normals/face_areas_normals_cpu.cpp
pytorch3d/csrc/gather_scatter/gather_scatter.cu
pytorch3d/csrc/gather_scatter/gather_scatter_cpu.cpp
pytorch3d/csrc/interp_face_attrs/interp_face_attrs.cu
pytorch3d/csrc/iou_box3d/iou_box3d.cu
pytorch3d/csrc/iou_box3d/iou_box3d_cpu.cpp
pytorch3d/csrc/knn/knn.cu
pytorch3d/csrc/knn/knn_cpu.cpp
pytorch3d/csrc/marching_cubes/marching_cubes.cu
pytorch3d/csrc/marching_cubes/marching_cubes_cpu.cpp
pytorch3d/csrc/mesh_normal_consistency/mesh_normal_consistency_cpu.cpp
pytorch3d/csrc/packed_to_padded_tensor/packed_to_padded_tensor.cu
pytorch3d/csrc/packed_to_padded_tensor/packed_to_padded_tensor_cpu.cpp
pytorch3d/csrc/point_mesh/point_mesh_cpu.cpp
pytorch3d/csrc/point_mesh/point_mesh_cuda.cu
pytorch3d/csrc/points_to_volumes/points_to_volumes.cu
pytorch3d/csrc/points_to_volumes/points_to_volumes_cpu.cpp
pytorch3d/csrc/pulsar/warnings.cpp
pytorch3d/csrc/pulsar/cuda/renderer.backward.gpu.cu
pytorch3d/csrc/pulsar/cuda/renderer.backward_dbg.gpu.cu
pytorch3d/csrc/pulsar/cuda/renderer.calc_gradients.gpu.cu
pipablepytorch3d-0.7.6.dist-info/LICENSE
pipablepytorch3d-0.7.6.dist-info/LICENSE-3RD-PARTY
pipablepytorch3d-0.7.6.dist-info/METADATA
pipablepytorch3d-0.7.6.dist-info/WHEEL
pipablepytorch3d-0.7.6.dist-info/entry_points.txt
pipablepytorch3d-0.7.6.dist-info/top_level.txt
pipablepytorch3d-0.7.6.dist-info/RECORD
