Metadata-Version: 2.1
Name: pipablepytorch3d
Version: 0.7.6
Summary: PyTorch3D is FAIR's library of reusable components for deep Learning with 3D data.
Home-page: https://github.com/facebookresearch/pytorch3d
Author: FAIR
License: BSD License
Project-URL: Homepage, https://github.com/orthly/pytorch3d
Project-URL: Bug Reports, https://github.com/orthly/pytorch3d
Project-URL: Source, https://github.com/orthly/pytorch3d
Classifier: Development Status :: 5 - Production/Stable
Classifier: Intended Audience :: Developers
Classifier: License :: OSI Approved :: BSD License
Classifier: Programming Language :: Python :: 3
Classifier: Programming Language :: Python :: 3.8
Classifier: Programming Language :: Python :: 3.9
Classifier: Programming Language :: Python :: 3.10
Classifier: Programming Language :: Python :: 3.11
Classifier: Programming Language :: Python :: 3 :: Only
Requires-Python: <3.12,>=3.8
License-File: LICENSE
License-File: LICENSE-3RD-PARTY
Requires-Dist: iopath
Requires-Dist: fvcore
Provides-Extra: all
Requires-Dist: imageio ; extra == 'all'
Requires-Dist: ipywidgets ; extra == 'all'
Requires-Dist: matplotlib ; extra == 'all'
Requires-Dist: tqdm >4.29.0 ; extra == 'all'
Provides-Extra: dev
Requires-Dist: flake8 ; extra == 'dev'
Requires-Dist: usort ; extra == 'dev'
Provides-Extra: implicitron
Requires-Dist: accelerate ; extra == 'implicitron'
Requires-Dist: hydra-core >=1.1 ; extra == 'implicitron'
Requires-Dist: lpips ; extra == 'implicitron'
Requires-Dist: matplotlib ; extra == 'implicitron'
Requires-Dist: tqdm >4.29.0 ; extra == 'implicitron'
Requires-Dist: visdom ; extra == 'implicitron'
